{
  "obsidian-admonition:insert-callout": [
    {
      "modifiers": [
        "Alt",
        "Mod",
        "Shift"
      ],
      "key": "C"
    }
  ],
  "editor:set-heading-1": [
    {
      "modifiers": [
        "Mod",
        "Shift"
      ],
      "key": "1"
    }
  ],
  "editor:set-heading-2": [
    {
      "modifiers": [
        "Mod",
        "Shift"
      ],
      "key": "2"
    }
  ],
  "editor:set-heading-3": [
    {
      "modifiers": [
        "Mod",
        "Shift"
      ],
      "key": "3"
    }
  ],
  "editor:set-heading-4": [
    {
      "modifiers": [
        "Mod",
        "Shift"
      ],
      "key": "4"
    }
  ],
  "editor:set-heading-5": [
    {
      "modifiers": [
        "Mod",
        "Shift"
      ],
      "key": "5"
    }
  ],
  "editor:set-heading-6": [
    {
      "modifiers": [
        "Mod",
        "Shift"
      ],
      "key": "6"
    }
  ],
  "editor:swap-line-up": [
    {
      "modifiers": [
        "Alt"
      ],
      "key": "ArrowUp"
    }
  ],
  "editor:swap-line-down": [
    {
      "modifiers": [
        "Alt"
      ],
      "key": "ArrowDown"
    }
  ],
  "editor:insert-callout": [
    {
      "modifiers": [
        "Mod",
        "Shift"
      ],
      "key": "C"
    }
  ],
  "obsidian-languagetool-plugin:ltcheck-text": [
    {
      "modifiers": [
        "Mod"
      ],
      "key": "."
    }
  ],
  "obsidian-languagetool-plugin:ltautocheck-text": [
    {
      "modifiers": [
        "Mod",
        "Shift"
      ],
      "key": "."
    }
  ],
  "obsidian-languagetool-plugin:ltjump-to-previous-suggestion": [
    {
      "modifiers": [
        "Alt",
        "Mod"
      ],
      "key": ","
    }
  ],
  "obsidian-languagetool-plugin:ltjump-to-next-suggestion": [
    {
      "modifiers": [
        "Alt",
        "Mod"
      ],
      "key": "."
    }
  ],
  "editor:toggle-numbered-list": [
    {
      "modifiers": [
        "Mod",
        "Shift"
      ],
      "key": "7"
    }
  ],
  "editor:toggle-bullet-list": [
    {
      "modifiers": [
        "Mod",
        "Shift"
      ],
      "key": "8"
    }
  ]
}